shiba/__init__.py
shiba/accountingmanagement.py
shiba/compat.py
shiba/inventorymanagement.py
shiba/marketplacemanagement.py
shiba/salesmanagement.py
shiba/shibaconnection.py
shiba/shibaexceptions.py
shiba/shibaresponseobject.py
shiba/shibatools.py
Shiba-1.2.1.dist-info/AUTHORS.rst
Shiba-1.2.1.dist-info/LICENSE.txt
Shiba-1.2.1.dist-info/METADATA
Shiba-1.2.1.dist-info/WHEEL
Shiba-1.2.1.dist-info/top_level.txt
Shiba-1.2.1.dist-info/zip-safe
Shiba-1.2.1.dist-info/RECORD
