Metadata-Version: 2.1
Name: Shiba
Version: 1.2.1
Summary: A Python API for PriceMinister WebServices
Home-page: https://github.com/ShibaAPI/shiba
Author: Nicolas Baccelli
Author-email: nicolas.baccelli@abc-culturel.fr
License: GPLv3
Keywords: api,priceminister,python,webservices
Classifier: License :: OSI Approved :: GNU General Public License v3 (GPLv3)
Classifier: Intended Audience :: Developers
Classifier: Programming Language :: Python :: 3
Classifier: Programming Language :: Python :: Implementation :: CPython
Classifier: Topic :: Software Development :: Libraries :: Python Modules
License-File: LICENSE.txt
License-File: AUTHORS.rst
Requires-Dist: requests
Requires-Dist: xmltodict
Requires-Dist: lxml
Requires-Dist: furl
Requires-Dist: ftfy
